nsj_rest_lib2/__init__.py
nsj_rest_lib2/exception.py
nsj_rest_lib2/redis_config.py
nsj_rest_lib2/settings.py
nsj_rest_lib2/compiler/__init__.py
nsj_rest_lib2/compiler/compiler.py
nsj_rest_lib2/compiler/compiler_structures.py
nsj_rest_lib2/compiler/dto_compiler.py
nsj_rest_lib2/compiler/entity_compiler.py
nsj_rest_lib2/compiler/function_get_delete_compiler.py
nsj_rest_lib2/compiler/function_insert_update_compiler.py
nsj_rest_lib2/compiler/function_model.py
nsj_rest_lib2/compiler/migration_compiler.py
nsj_rest_lib2/compiler/migration_compiler_alter_table.py
nsj_rest_lib2/compiler/migration_compiler_create_table.py
nsj_rest_lib2/compiler/migration_compiler_util.py
nsj_rest_lib2/compiler/model.py
nsj_rest_lib2/compiler/property_compiler.py
nsj_rest_lib2/compiler/response_dto_compiler.py
nsj_rest_lib2/compiler/edl_model/__init__.py
nsj_rest_lib2/compiler/edl_model/ai_entity_edl.py
nsj_rest_lib2/compiler/edl_model/api_model.py
nsj_rest_lib2/compiler/edl_model/column_meta_model.py
nsj_rest_lib2/compiler/edl_model/entity_model.py
nsj_rest_lib2/compiler/edl_model/entity_model_base.py
nsj_rest_lib2/compiler/edl_model/entity_model_root.py
nsj_rest_lib2/compiler/edl_model/index_model.py
nsj_rest_lib2/compiler/edl_model/primitives.py
nsj_rest_lib2/compiler/edl_model/property_meta_model.py
nsj_rest_lib2/compiler/edl_model/repository_model.py
nsj_rest_lib2/compiler/edl_model/trait_property_meta_model.py
nsj_rest_lib2/compiler/util/__init__.py
nsj_rest_lib2/compiler/util/relation_ref.py
nsj_rest_lib2/compiler/util/str_util.py
nsj_rest_lib2/compiler/util/type_naming_util.py
nsj_rest_lib2/compiler/util/type_util.py
nsj_rest_lib2/controller/__init__.py
nsj_rest_lib2/controller/dynamic_controller.py
nsj_rest_lib2/dto/__init__.py
nsj_rest_lib2/dto/escopo_dto.py
nsj_rest_lib2/entity/__init__.py
nsj_rest_lib2/entity/escopo_entity.py
nsj_rest_lib2/service/__init__.py
nsj_rest_lib2/service/entity_config_writer.py
nsj_rest_lib2/service/entity_loader.py
nsj_rest_lib2-0.0.36.dist-info/METADATA
nsj_rest_lib2-0.0.36.dist-info/WHEEL
nsj_rest_lib2-0.0.36.dist-info/top_level.txt
nsj_rest_lib2-0.0.36.dist-info/RECORD
