Metadata-Version: 2.4
Name: nsj_rest_lib2
Version: 0.0.36
Summary: Biblioteca para permitir a distribuição de rotas dinâmicas numa API, configuradas por meio de EDLs declarativos (em formato JSON).
Home-page: https://github.com/Nasajon/nsj_rest_lib2
Author: Nasajon Sistemas
Author-email: contact.dev@nasajon.com.br
Project-URL: Source, https://github.com/Nasajon/nsj_rest_lib2
Classifier: Development Status :: 3 - Alpha
Classifier: Intended Audience :: Developers
Classifier: Topic :: Software Development :: Libraries
Classifier: Programming Language :: Python :: 3
Requires-Python: >=3.4
Requires-Dist: nsj-rest-lib<7.0.0,>=5.1.3
Requires-Dist: redis<7.0.0,>=6.4.0
Requires-Dist: nsj-multi-database-lib<3.0.0,>=2.0.1
Requires-Dist: pydantic<3.0.0,>=2.11.9
Requires-Dist: black<26.0.0,>=25.1.0
Requires-Dist: pyyaml<7.0.0,>=6.0.3
